{
  "nStates": 13,
  "startState": 1,
  "finalStates": [13],
  "sigma": ["1"],
  "gamma": ["1", "B", "^", "@", "#"],
  "leftMarker": "B",
  "rightMarker": "B",
  "transitions": [
    {"from": 1,  "to": 2,  "by": "1", "writing": "1", "direction": "RIGHT" },
    {"from": 2,  "to": 3,  "by": "1", "writing": "@", "direction": "LEFT" },
    {"from": 3,  "to": 3,  "by": "1", "writing": "1", "direction": "LEFT" },
    {"from": 3,  "to": 4,  "by": "B", "writing": "B", "direction": "RIGHT" },
    {"from": 3,  "to": 4,  "by": "#", "writing": "#", "direction": "RIGHT" },
    {"from": 3,  "to": 4,  "by": "^", "writing": "^", "direction": "RIGHT" },
    {"from": 3,  "to": 4,  "by": "@", "writing": "@", "direction": "RIGHT" },
    {"from": 4,  "to": 5,  "by": "1", "writing": "#", "direction": "RIGHT" },
    {"from": 5,  "to": 5,  "by": "1", "writing": "1", "direction": "RIGHT" },
    {"from": 5,  "to": 7,  "by": "@", "writing": "@", "direction": "RIGHT" },
    {"from": 5,  "to": 7,  "by": "^", "writing": "^", "direction": "RIGHT" },
    {"from": 7,  "to": 8,  "by": "B", "writing": "B", "direction": "LEFT" },
    {"from": 8,  "to": 10, "by": "#", "writing": "1", "direction": "LEFT" },
    {"from": 8,  "to": 1,  "by": "^", "writing": "^", "direction": "RIGHT" },
    {"from": 8,  "to": 1,  "by": "@", "writing": "@", "direction": "RIGHT" },
    {"from": 7,  "to": 7,  "by": "#", "writing": "#", "direction": "RIGHT" },
    {"from": 7,  "to": 9,  "by": "1", "writing": "#", "direction": "LEFT" },
    {"from": 9,  "to": 9,  "by": "#", "writing": "#", "direction": "LEFT" },
    {"from": 9,  "to": 3,  "by": "^", "writing": "^", "direction": "LEFT" },
    {"from": 9,  "to": 3,  "by": "@", "writing": "@", "direction": "LEFT" },
    {"from": 4,  "to": 6,  "by": "^", "writing": "^", "direction": "RIGHT" },
    {"from": 4,  "to": 6,  "by": "@", "writing": "@", "direction": "RIGHT" },
    {"from": 6,  "to": 6,  "by": "#", "writing": "1", "direction": "RIGHT" },
    {"from": 6,  "to": 3,  "by": "1", "writing": "^", "direction": "LEFT" },
    {"from": 6,  "to": 10, "by": "B", "writing": "B", "direction": "LEFT" },
    {"from": 10, "to": 10, "by": "#", "writing": "1", "direction": "LEFT" },
    {"from": 10, "to": 10, "by": "^", "writing": "1", "direction": "LEFT" },
    {"from": 10, "to": 10, "by": "1", "writing": "1", "direction": "LEFT" },
    {"from": 10, "to": 11, "by": "B", "writing": "B", "direction": "RIGHT" },
    {"from": 11, "to": 11, "by": "1", "writing": "1", "direction": "RIGHT" },
    {"from": 11, "to": 12, "by": "@", "writing": "1", "direction": "RIGHT" },
    {"from": 12, "to": 13, "by": "B", "writing": "B", "direction": "LEFT" },
    {"from": 12, "to": 3,  "by": "1", "writing": "@", "direction": "LEFT" }
  ]
}